tgp/__init__.py
tgp/_static_version.py
tgp/_version.py
tgp/bias_correction.py
tgp/common.py
tgp/data_naming.yaml
tgp/frequency_correction.py
tgp/one.py
tgp/prepare.py
tgp/two.py
tgp/widgets.py
tgp/plot/__init__.py
tgp/plot/one.py
tgp/plot/paper.py
tgp/plot/two.py
tgp/plot/zbp.py
azure_quantum_tgp-1.1.0.dist-info/LICENSE
azure_quantum_tgp-1.1.0.dist-info/METADATA
azure_quantum_tgp-1.1.0.dist-info/WHEEL
azure_quantum_tgp-1.1.0.dist-info/top_level.txt
azure_quantum_tgp-1.1.0.dist-info/RECORD
